example/__init__.py
example/download.py
example/huobi_ex.py
example/juejin.py
example/test2.py
notestock/__init__.py
notestock/dataset/__init__.py
notestock/dataset/databasestock.py
notestock/dataset/dataset.py
notestock/dataset/download.py
notestock/dataset/run.py
notestock/echarts/DayChart.py
notestock/echarts/__init__.py
notestock-0.2.9.dist-info/METADATA
notestock-0.2.9.dist-info/WHEEL
notestock-0.2.9.dist-info/top_level.txt
notestock-0.2.9.dist-info/RECORD
