Metadata-Version: 2.1
Name: notestock
Version: 0.2.9
Summary: notestock
Home-page: https://github.com/1007530194
Author: niult
Author-email: 1007530194@qq.com
License: UNKNOWN
Platform: UNKNOWN
Requires-Dist: tushare
